a4e/__init__.py
a4e/cli.py
a4e/core.py
a4e/dev_runner.py
a4e/server.py
a4e/cli_commands/__init__.py
a4e/cli_commands/add.py
a4e/cli_commands/deploy.py
a4e/cli_commands/dev.py
a4e/cli_commands/info.py
a4e/cli_commands/init.py
a4e/cli_commands/list.py
a4e/cli_commands/mcp.py
a4e/cli_commands/remove.py
a4e/cli_commands/update.py
a4e/cli_commands/validate.py
a4e/templates/agent.md.j2
a4e/templates/agent.py.j2
a4e/templates/agents.md.j2
a4e/templates/metadata.json.j2
a4e/templates/prompt.md.j2
a4e/templates/support_module.py.j2
a4e/templates/tool.py.j2
a4e/templates/view.tsx.j2
a4e/templates/prompts/agent.md.j2
a4e/templates/skills/agents.md.j2
a4e/templates/skills/skill.md.j2
a4e/templates/tools/agent.md.j2
a4e/templates/views/agent.md.j2
a4e/tools/__init__.py
a4e/tools/agent_tools/__init__.py
a4e/tools/agent_tools/add_support_module.py
a4e/tools/agent_tools/add_tool.py
a4e/tools/agent_tools/list_tools.py
a4e/tools/agent_tools/remove_tool.py
a4e/tools/agent_tools/update_tool.py
a4e/tools/deploy/__init__.py
a4e/tools/deploy/deploy.py
a4e/tools/dev/__init__.py
a4e/tools/dev/check_environment.py
a4e/tools/dev/dev_start.py
a4e/tools/dev/dev_stop.py
a4e/tools/project/__init__.py
a4e/tools/project/get_agent_info.py
a4e/tools/project/get_instructions.py
a4e/tools/project/initialize_project.py
a4e/tools/schemas/__init__.py
a4e/tools/schemas/generate_schemas.py
a4e/tools/skills/__init__.py
a4e/tools/skills/add_skill.py
a4e/tools/skills/helpers.py
a4e/tools/skills/list_skills.py
a4e/tools/skills/remove_skill.py
a4e/tools/skills/update_skill.py
a4e/tools/validation/__init__.py
a4e/tools/validation/validate.py
a4e/tools/views/__init__.py
a4e/tools/views/add_view.py
a4e/tools/views/helpers.py
a4e/tools/views/list_views.py
a4e/tools/views/remove_view.py
a4e/tools/views/update_view.py
a4e/utils/dev_manager.py
a4e/utils/schema_generator.py
a4e-0.1.0.dist-info/licenses/LICENSE
a4e-0.1.0.dist-info/METADATA
a4e-0.1.0.dist-info/WHEEL
a4e-0.1.0.dist-info/entry_points.txt
a4e-0.1.0.dist-info/top_level.txt
a4e-0.1.0.dist-info/RECORD
