Metadata-Version: 2.4
Name: a4e
Version: 0.1.0
Summary: A comprehensive MCP server toolkit for building, managing, and running AI agents compatible with the A4E ecosystem.
Author-email: Angel Castiblanco <angel.castiblanco@simetrik.com>, Michael Guerrero <michael.guerrero@simetrik.com>, Jonathan Batista <jonathan.batista@simetrik.com>
Maintainer-email: Simetrik <angel.castiblanco@simetrik.com>
License-Expression: MIT
Project-URL: Homepage, https://github.com/simetrik-inc-public/a4e-mcp-server
Project-URL: Documentation, https://github.com/simetrik-inc-public/a4e-mcp-server#readme
Project-URL: Repository, https://github.com/simetrik-inc-public/a4e-mcp-server
Project-URL: Issues, https://github.com/simetrik-inc-public/a4e-mcp-server/issues
Keywords: mcp,ai,agents,llm,model-context-protocol,a4e,cursor,claude,simetrik
Classifier: Development Status :: 4 - Beta
Classifier: Intended Audience :: Developers
Classifier: Operating System :: OS Independent
Classifier: Programming Language :: Python :: 3
Classifier: Programming Language :: Python :: 3.11
Classifier: Programming Language :: Python :: 3.12
Classifier: Topic :: Software Development :: Libraries :: Python Modules
Classifier: Topic :: Scientific/Engineering :: Artificial Intelligence
Requires-Python: >=3.11
License-File: LICENSE
Requires-Dist: jinja2>=3.1.6
Requires-Dist: mcp[cli]>=1.22.0
Requires-Dist: pydantic>=2.12.4
Requires-Dist: pyngrok>=7.5.0
Requires-Dist: pyperclip>=1.11.0
Requires-Dist: pyyaml>=6.0.3
Requires-Dist: rich>=13.0.0
Requires-Dist: sse-starlette>=3.0.3
Requires-Dist: typer>=0.20.0
Requires-Dist: watchdog>=6.0.0
Dynamic: license-file
